tangram_ship162-0.2.1.dist-info/METADATA
tangram_ship162-0.2.1.dist-info/WHEEL
tangram_ship162-0.2.1.dist-info/entry_points.txt
tangram_ship162/ShipCountWidget.vue
tangram_ship162/ShipInfoWidget.vue
tangram_ship162/ShipLayer.vue
tangram_ship162/ShipTrailLayer.vue
tangram_ship162/__init__.py
tangram_ship162/_ships.cpython-310-powerpc64le-linux-gnu.so
tangram_ship162/_ships.pyi
tangram_ship162/index.ts
tangram_ship162/store.ts
tangram_ship162-0.2.1.dist-info/RECORD
