Metadata-Version: 2.4
Name: tangram_ship162
Version: 0.2.1
Classifier: Development Status :: 4 - Beta
Classifier: Intended Audience :: Science/Research
Classifier: License :: OSI Approved :: GNU Affero General Public License v3
Classifier: Programming Language :: Python :: 3
Classifier: Programming Language :: Python :: 3.10
Classifier: Programming Language :: Python :: 3.11
Classifier: Programming Language :: Python :: 3.12
Classifier: Programming Language :: Python :: 3.13
Classifier: Programming Language :: Python :: 3.14
Classifier: Programming Language :: Rust
Classifier: Topic :: Scientific/Engineering :: Visualization
Requires-Dist: tangram-core>=0.2.0
Requires-Dist: polars[deltalake] ; extra == 'history'
Provides-Extra: history
Summary: AIS maritime data integration plugin for tangram
Home-Page: https://mode-s.org/tangram/
Author-email: Abraham Cheung <abraham@ylcheung.com>
License-Expression: AGPL-3.0
Requires-Python: >=3.10
